LICENSE
MANIFEST.in
README.md
Releases
download_it.py
prompt_user.py
pysub-dl
setup.py
pysub_dl.egg-info/PKG-INFO
pysub_dl.egg-info/SOURCES.txt
pysub_dl.egg-info/dependency_links.txt
pysub_dl.egg-info/top_level.txt