Metadata-Version: 1.1
Name: pysub-dl
Version: 0.3.2
Summary: Script to download movie subtitles automatically
Home-page: http://iamsudip.github.io/pysub-dl
Author: iamsudip
Author-email: iamsudip@programmer.net
License: MIT
Platform: Linux
Classifier: Development Status :: 5 - Production/Stable
Classifier: Environment :: Console
Classifier: License :: OSI Approved :: MIT License
Classifier: Intended Audience :: End Users/Desktop
Classifier: Topic :: Multimedia :: Video
Classifier: Topic :: Utilities
Classifier: Natural Language :: English
Classifier: Programming Language :: Python :: 2.7
